viggonuvemfiscal/__init__.py
viggonuvemfiscal/resources.py
viggonuvemfiscal/subsystem/__init__.py
viggonuvemfiscal/subsystem/controle/__init__.py
viggonuvemfiscal/subsystem/controle/configuracao_nuvem_fiscal/__init__.py
viggonuvemfiscal/subsystem/controle/configuracao_nuvem_fiscal/manager.py
viggonuvemfiscal/subsystem/controle/configuracao_nuvem_fiscal/resource.py
viggonuvemfiscal/subsystem/controle/configuracao_nuvem_fiscal/router.py
viggonuvemfiscal/subsystem/controle/nuvem_fiscal/__init__.py
viggonuvemfiscal/subsystem/controle/nuvem_fiscal/controller.py
viggonuvemfiscal/subsystem/controle/nuvem_fiscal/manager.py
viggonuvemfiscal/subsystem/controle/nuvem_fiscal/resource.py
viggonuvemfiscal/subsystem/controle/nuvem_fiscal/router.py
viggonuvemfiscal-1.2.0.dist-info/AUTHORS
viggonuvemfiscal-1.2.0.dist-info/METADATA
viggonuvemfiscal-1.2.0.dist-info/WHEEL
viggonuvemfiscal-1.2.0.dist-info/top_level.txt
viggonuvemfiscal-1.2.0.dist-info/RECORD
