Metadata-Version: 2.1
Name: viggonuvemfiscal
Version: 1.2.0
Summary: ViggoNuvemFiscal backend Flask REST service
Home-page: UNKNOWN
License: UNKNOWN
Platform: UNKNOWN
License-File: AUTHORS
Requires-Dist: viggocore<2.0.0,>=1.0.0
Requires-Dist: flask-cors
